django_docutils/__about__.py
django_docutils/__init__.py
django_docutils/exc.py
django_docutils/py.typed
django_docutils/template.py
django_docutils/views.py
django_docutils/_internal/__init__.py
django_docutils/_internal/types.py
django_docutils/lib/__init__.py
django_docutils/lib/publisher.py
django_docutils/lib/settings.py
django_docutils/lib/text.py
django_docutils/lib/types.py
django_docutils/lib/utils.py
django_docutils/lib/views.py
django_docutils/lib/writers.py
django_docutils/lib/directives/__init__.py
django_docutils/lib/directives/code.py
django_docutils/lib/directives/registry.py
django_docutils/lib/metadata/__init__.py
django_docutils/lib/metadata/extract.py
django_docutils/lib/metadata/process.py
django_docutils/lib/metadata/processors.py
django_docutils/lib/metadata/tests/__init__.py
django_docutils/lib/metadata/tests/test_extract.py
django_docutils/lib/metadata/tests/test_process.py
django_docutils/lib/roles/__init__.py
django_docutils/lib/roles/common.py
django_docutils/lib/roles/email.py
django_docutils/lib/roles/file.py
django_docutils/lib/roles/github.py
django_docutils/lib/roles/hackernews.py
django_docutils/lib/roles/kbd.py
django_docutils/lib/roles/leanpub.py
django_docutils/lib/roles/pypi.py
django_docutils/lib/roles/readthedocs.py
django_docutils/lib/roles/registry.py
django_docutils/lib/roles/twitter.py
django_docutils/lib/roles/types.py
django_docutils/lib/roles/url.py
django_docutils/lib/roles/wikipedia.py
django_docutils/lib/templates/rst/base.html
django_docutils/lib/templates/rst/raw.html
django_docutils/lib/tests/__init__.py
django_docutils/lib/tests/test_utils.py
django_docutils/lib/tests/test_writers.py
django_docutils/lib/transforms/__init__.py
django_docutils/lib/transforms/code.py
django_docutils/lib/transforms/toc.py
django_docutils/templatetags/__init__.py
django_docutils/templatetags/django_docutils.py
django_docutils-0.28.0.dist-info/METADATA
django_docutils-0.28.0.dist-info/WHEEL
django_docutils-0.28.0.dist-info/licenses/LICENSE
django_docutils-0.28.0.dist-info/RECORD
