Metadata-Version: 2.4
Name: django-docutils
Version: 0.28.0
Summary: Docutils (a.k.a. reStructuredText, reST, RST) support for django.
Author-email: Tony Narlock <tony@git-pull.com>
License: MIT
License-File: LICENSE
Keywords: django,docutils,reST,reStructuredText,rst
Classifier: Development Status :: 2 - Pre-Alpha
Classifier: Framework :: Django
Classifier: Framework :: Django :: 4.2
Classifier: Framework :: Django :: 5.0
Classifier: Framework :: Django :: 5.1
Classifier: Intended Audience :: Developers
Classifier: License :: OSI Approved :: MIT License
Classifier: Natural Language :: English
Classifier: Programming Language :: Python :: 3
Classifier: Programming Language :: Python :: 3.9
Classifier: Programming Language :: Python :: 3.10
Classifier: Programming Language :: Python :: 3.11
Classifier: Programming Language :: Python :: 3.12
Classifier: Programming Language :: Python :: 3.13
Classifier: Typing :: Typed
Requires-Python: <4.0,>=3.9
Requires-Dist: django>=4.2
Requires-Dist: docutils
Requires-Dist: pygments<3
Provides-Extra: pytz
Requires-Dist: pytz; extra == 'pytz'
